{
    "J00": "Rhinopharyngite aiguë (rhume banal)",
    "J06.9": "Infection des voies respiratoires supérieures",
    "J45.0": "Asthme à prédominance allergique",
    "I10": "Hypertension essentielle (primaire)",
    "E11.9": "Diabète sucré de type 2, sans complication",
    "K21.9": "Reflux gastro-œsophagien sans œsophagite",
    "M54.5": "Lombalgie",
    "R50.9": "Fièvre, sans précision",
    "A09": "Diarrhée et gastro-entérite d'origine présumée infectieuse",
    "H10.9": "Conjonctivite, sans précision"
}
